{
  "id": "open-pending-claim-ttl-p1-a1-p1-a2",
  "name": "open-pending-claim-ttl-p1-a1-p1-a2",
  "title": "订单生命周期收尾:幽灵 open 订单驱逐与 pending claim TTL (P1-A1+P1-A2)",
  "description": "",
  "status": "completed",
  "dev_type": null,
  "scope": null,
  "package": null,
  "priority": "P2",
  "creator": "codex-agent",
  "assignee": "codex-agent",
  "createdAt": "2026-06-11",
  "completedAt": "2026-06-11",
  "branch": null,
  "base_branch": "main",
  "worktree_path": null,
  "commit": null,
  "pr_url": null,
  "subtasks": [],
  "children": [],
  "parent": null,
  "relatedFiles": [],
  "notes": "",
  "meta": {}
}